sequencelib.py
sequencelib-2.23.2.dist-info/licenses/LICENSE
sequencelib-2.23.2.dist-info/METADATA
sequencelib-2.23.2.dist-info/WHEEL
sequencelib-2.23.2.dist-info/top_level.txt
sequencelib-2.23.2.dist-info/RECORD
