Metadata-Version: 2.4
Name: sequencelib
Version: 2.23.2
Summary: Read, write, and analyze biological sequences
Home-page: https://github.com/agormp/sequencelib
Author: Anders Gorm Pedersen
Author-email: agpe@dtu.dk
Classifier: Programming Language :: Python :: 3
Classifier: License :: OSI Approved :: GNU General Public License v3 (GPLv3)
Classifier: Operating System :: OS Independent
Requires-Python: >=3.6
License-File: LICENSE
Requires-Dist: numpy
Requires-Dist: Levenshtein
Dynamic: license-file
